minisignxml/__init__.py
minisignxml/config.py
minisignxml/errors.py
minisignxml/internal/__init__.py
minisignxml/internal/constants.py
minisignxml/internal/namespaces.py
minisignxml/internal/utils.py
minisignxml/py.typed
minisignxml/sign.py
minisignxml/verify.py
minisignxml-26.1.dist-info/METADATA
minisignxml-26.1.dist-info/WHEEL
minisignxml-26.1.dist-info/licenses/LICENSE
minisignxml-26.1.dist-info/RECORD
