Metadata-Version: 2.4
Name: minisignxml
Version: 26.1
Summary: Minimal XML signature and verification, intended for use with SAML2
License: Apache-2.0
License-File: LICENSE
Author: Jonas Obrist
Author-email: jonas.obrist@hennge.com
Requires-Python: >=3.10,<4.0
Classifier: Development Status :: 5 - Production/Stable
Classifier: Intended Audience :: Developers
Classifier: License :: OSI Approved :: Apache Software License
Classifier: Programming Language :: Python :: 3
Classifier: Programming Language :: Python :: 3.10
Classifier: Programming Language :: Python :: 3.11
Classifier: Programming Language :: Python :: 3.12
Classifier: Programming Language :: Python :: 3.13
Classifier: Programming Language :: Python :: 3.14
Classifier: Programming Language :: Python :: 3 :: Only
Classifier: Topic :: Security :: Cryptography
Classifier: Topic :: Text Processing :: Markup :: XML
Classifier: Typing :: Typed
Requires-Dist: cryptography (>=46.0)
Requires-Dist: defusedxml (>=0.7.1)
Requires-Dist: lxml (>=6.0,<7.0)
Project-URL: Homepage, https://github.com/HENNGE/minisignxml
Project-URL: Repository, https://github.com/HENNGE/minisignxml
